{
  "$schema": "https://developer.microsoft.com/json-schemas/fabric/item/report/definition/visualContainer/2.5.0/schema.json",
  "name": "66edfe884875036a3921",
  "position": {
    "x": 306.8041237113402,
    "y": 14.226804123711339,
    "z": 3000,
    "height": 300,
    "width": 541.85567010309273
  },
  "visual": {
    "visualType": "tableEx",
    "query": {
      "queryState": {
        "Values": {
          "projections": [
            {
              "field": {
                "Column": {
                  "Expression": {
                    "SourceRef": {
                      "Entity": "DIVISIONS_D"
                    }
                  },
                  "Property": "Company"
                }
              },
              "queryRef": "DIVISIONS_D.Company",
              "nativeQueryRef": "Company"
            },
            {
              "field": {
                "Column": {
                  "Expression": {
                    "SourceRef": {
                      "Entity": "DIVISIONS_D"
                    }
                  },
                  "Property": "Division"
                }
              },
              "queryRef": "DIVISIONS_D.Division",
              "nativeQueryRef": "Division"
            },
            {
              "field": {
                "Column": {
                  "Expression": {
                    "SourceRef": {
                      "Entity": "TM_CustomerMonth_Amend_F"
                    }
                  },
                  "Property": "Divisions"
                }
              },
              "queryRef": "TM_CustomerMonth_Amend_F.Divisions",
              "nativeQueryRef": "Divisions"
            },
            {
              "field": {
                "Aggregation": {
                  "Expression": {
                    "Column": {
                      "Expression": {
                        "SourceRef": {
                          "Entity": "TM_CustomerMonth_Amend_F"
                        }
                      },
                      "Property": "Revenue Amount"
                    }
                  },
                  "Function": 0
                }
              },
              "queryRef": "Sum(TM_CustomerMonth_Amend_F.Revenue Amount)",
              "nativeQueryRef": "Sum of Revenue Amount"
            }
          ]
        }
      }
    },
    "drillFilterOtherVisuals": true
  }
}