{
  "$schema": "https://developer.microsoft.com/json-schemas/fabric/item/report/definition/visualContainer/2.4.0/schema.json",
  "name": "1fa3730d658d1c9e95a5",
  "position": {
    "x": 758,
    "y": 177,
    "z": 4000,
    "height": 320,
    "width": 1117,
    "tabOrder": 0
  },
  "visual": {
    "visualType": "pivotTable",
    "query": {
      "queryState": {
        "Rows": {
          "projections": [
            {
              "field": {
                "Column": {
                  "Expression": {
                    "SourceRef": {
                      "Entity": "FYCALENDAR_D"
                    }
                  },
                  "Property": "Fiscal Year"
                }
              },
              "queryRef": "FYCALENDAR_D.Fiscal Year",
              "nativeQueryRef": "Fiscal Year",
              "active": true
            },
            {
              "field": {
                "Column": {
                  "Expression": {
                    "SourceRef": {
                      "Entity": "FYCALENDAR_D"
                    }
                  },
                  "Property": "MMM Label"
                }
              },
              "queryRef": "FYCALENDAR_D.MMM Label",
              "nativeQueryRef": "MMM Label",
              "active": false
            }
          ]
        },
        "Values": {
          "projections": [
            {
              "field": {
                "Measure": {
                  "Expression": {
                    "SourceRef": {
                      "Entity": "_Key Measures"
                    }
                  },
                  "Property": "Net Promoter Score"
                }
              },
              "queryRef": "_Key Measures.Net Promoter Score",
              "nativeQueryRef": "Net Promoter Score"
            },
            {
              "field": {
                "Measure": {
                  "Expression": {
                    "SourceRef": {
                      "Entity": "_Key Measures"
                    }
                  },
                  "Property": "Net Revenue Retention % (R12M As Of)"
                }
              },
              "queryRef": "_Key Measures.Net Revenue Retention % (R12M As Of)",
              "nativeQueryRef": "Net Revenue Retention % (R12M As Of)"
            },
            {
              "field": {
                "Measure": {
                  "Expression": {
                    "SourceRef": {
                      "Entity": "_Key Measures"
                    }
                  },
                  "Property": "Gross Revenue Retention % (R12M As Of)"
                }
              },
              "queryRef": "_Key Measures.Gross Revenue Retention % (R12M As Of)",
              "nativeQueryRef": "Gross Revenue Retention % (R12M As Of)"
            },
            {
              "field": {
                "Measure": {
                  "Expression": {
                    "SourceRef": {
                      "Entity": "_Key Measures"
                    }
                  },
                  "Property": "Logo Retention % (SC) (R12M As Of)"
                }
              },
              "queryRef": "_Key Measures.Logo Retention % (SC) (R12M As Of)",
              "nativeQueryRef": "Logo Retention % (SC) (R12M As Of)"
            },
            {
              "field": {
                "Measure": {
                  "Expression": {
                    "SourceRef": {
                      "Entity": "_Key Measures"
                    }
                  },
                  "Property": "Net Revenue Retention Trend vs PY (R12M As Of)"
                }
              },
              "queryRef": "_Key Measures.Net Revenue Retention Trend vs PY (R12M As Of)",
              "nativeQueryRef": "Net Revenue Retention Trend vs PY (R12M As Of)"
            }
          ]
        }
      }
    },
    "expansionStates": [
      {
        "roles": [
          "Rows"
        ],
        "levels": [
          {
            "queryRefs": [
              "FYCALENDAR_D.Fiscal Year"
            ],
            "isCollapsed": true,
            "identityKeys": [
              {
                "Column": {
                  "Expression": {
                    "SourceRef": {
                      "Entity": "FYCALENDAR_D"
                    }
                  },
                  "Property": "Fiscal Year"
                }
              }
            ],
            "isPinned": true
          },
          {
            "queryRefs": [
              "FYCALENDAR_D.MMM Label"
            ],
            "isCollapsed": true,
            "isPinned": true
          }
        ],
        "root": {}
      }
    ],
    "drillFilterOtherVisuals": true
  },
  "filterConfig": {
    "filters": [
      {
        "name": "b0153076b7e166336327",
        "field": {
          "Column": {
            "Expression": {
              "SourceRef": {
                "Entity": "FYCALENDAR_D"
              }
            },
            "Property": "Fiscal Year"
          }
        },
        "type": "Advanced",
        "filter": {
          "Version": 2,
          "From": [
            {
              "Name": "f",
              "Entity": "FYCALENDAR_D",
              "Type": 0
            }
          ],
          "Where": [
            {
              "Condition": {
                "Comparison": {
                  "ComparisonKind": 1,
                  "Left": {
                    "Column": {
                      "Expression": {
                        "SourceRef": {
                          "Source": "f"
                        }
                      },
                      "Property": "Fiscal Year"
                    }
                  },
                  "Right": {
                    "Literal": {
                      "Value": "2023L"
                    }
                  }
                }
              }
            }
          ]
        },
        "isLockedInViewMode": true
      },
      {
        "name": "8b8eec3d936b06e80332",
        "field": {
          "Column": {
            "Expression": {
              "SourceRef": {
                "Entity": "FYCALENDAR_D"
              }
            },
            "Property": "Date"
          }
        },
        "type": "Advanced",
        "filter": {
          "Version": 2,
          "From": [
            {
              "Name": "f",
              "Entity": "FYCALENDAR_D",
              "Type": 0
            }
          ],
          "Where": [
            {
              "Condition": {
                "Comparison": {
                  "ComparisonKind": 3,
                  "Left": {
                    "Column": {
                      "Expression": {
                        "SourceRef": {
                          "Source": "f"
                        }
                      },
                      "Property": "Date"
                    }
                  },
                  "Right": {
                    "DateSpan": {
                      "Expression": {
                        "Literal": {
                          "Value": "datetime'2025-12-01T00:00:00'"
                        }
                      },
                      "TimeUnit": 5
                    }
                  }
                }
              }
            }
          ]
        },
        "howCreated": "User"
      }
    ]
  }
}